aspdone/__init__.py
aspdone/ALL_PRACT_PROPER/PRACTICAL_NO_01_new[1].pdf
aspdone/ALL_PRACT_PROPER/PRACTICAL_NO_02_new[1].pdf
aspdone/ALL_PRACT_PROPER/PRACTICAL_NO_03_-_new[1].pdf
aspdone/ALL_PRACT_PROPER/PRACTICAL_NO_04_-_new[1].pdf
aspdone/ALL_PRACT_PROPER/PRACTICAL_NO_05_new[1].pdf
aspdone/ALL_PRACT_PROPER/PRACTICAL_NO_06_new[1].pdf
aspdone/ALL_PRACT_PROPER/PRACTICAL_NO_07_new[1].pdf
aspdone/ALL_PRACT_PROPER/PRACTICAL_NO_08[2].pdf
aspdone/ALL_PRACT_PROPER/PRACTICAL_NO_09[2].pdf
aspdone/ALL_PRACT_PROPER/PRACTICAL_NO_10[1].pdf
aspdone/GUIDE/HELPCON.pdf
aspdone-0.2.dist-info/METADATA
aspdone-0.2.dist-info/WHEEL
aspdone-0.2.dist-info/top_level.txt
aspdone-0.2.dist-info/RECORD
